kwenta_sdk/__init__.py
kwenta_sdk/contracts.py
kwenta_sdk/kwenta_config.py
kwenta_sdk/kwenta_sdk.py
kwenta_sdk/utilities.py
kwenta_sdk/json/PerpsV2Market.json
kwenta_sdk/json/PerpsV2MarketData.json
kwenta_sdk/json/__init__.py
kwenta_sdk/json/sUSD.json
kwenta_sdk-1.0.0.dist-info/METADATA
kwenta_sdk-1.0.0.dist-info/WHEEL
kwenta_sdk-1.0.0.dist-info/top_level.txt
kwenta_sdk-1.0.0.dist-info/RECORD
